{
  "node": {
    "b67bb1a8a350b78bade5e28c56c092d66706ad4a": {
      "workers": {
        "app/admin/projects/page": "(rsc)/./node_modules/next/dist/build/webpack/loaders/next-flight-action-entry-loader.js?actions=%5B%5B%22C%3A%5C%5CUsers%5C%5Ckompik%5C%5CDocuments%5C%5CVScode%5C%5Csezony%5C%5Csrc%5C%5Capp%5C%5Cadmin%5C%5Cprojects%5C%5Cactions.ts%22%2C%5B%22saveProjectAction%22%2C%22deleteProjectAction%22%5D%5D%5D&__client_imported__=!",
        "app/admin/projects/[id]/edit/page": "(rsc)/./node_modules/next/dist/build/webpack/loaders/next-flight-action-entry-loader.js?actions=%5B%5B%22C%3A%5C%5CUsers%5C%5Ckompik%5C%5CDocuments%5C%5CVScode%5C%5Csezony%5C%5Csrc%5C%5Capp%5C%5Cadmin%5C%5Cprojects%5C%5Cactions.ts%22%2C%5B%22saveProjectAction%22%2C%22deleteProjectAction%22%5D%5D%5D&__client_imported__=!"
      },
      "layer": {
        "app/admin/projects/page": "rsc",
        "app/admin/projects/[id]/edit/page": "rsc"
      }
    },
    "d70a29b1ad0ade14c8f930893a3cf003bc8a3915": {
      "workers": {
        "app/admin/projects/page": "(rsc)/./node_modules/next/dist/build/webpack/loaders/next-flight-action-entry-loader.js?actions=%5B%5B%22C%3A%5C%5CUsers%5C%5Ckompik%5C%5CDocuments%5C%5CVScode%5C%5Csezony%5C%5Csrc%5C%5Capp%5C%5Cadmin%5C%5Cprojects%5C%5Cactions.ts%22%2C%5B%22saveProjectAction%22%2C%22deleteProjectAction%22%5D%5D%5D&__client_imported__=!",
        "app/admin/projects/[id]/edit/page": "(rsc)/./node_modules/next/dist/build/webpack/loaders/next-flight-action-entry-loader.js?actions=%5B%5B%22C%3A%5C%5CUsers%5C%5Ckompik%5C%5CDocuments%5C%5CVScode%5C%5Csezony%5C%5Csrc%5C%5Capp%5C%5Cadmin%5C%5Cprojects%5C%5Cactions.ts%22%2C%5B%22saveProjectAction%22%2C%22deleteProjectAction%22%5D%5D%5D&__client_imported__=!"
      },
      "layer": {
        "app/admin/projects/page": "rsc",
        "app/admin/projects/[id]/edit/page": "rsc"
      }
    },
    "a1655fd9ff31414bd929999a936dc971b157233d": {
      "workers": {
        "app/admin/requests/page": "(rsc)/./node_modules/next/dist/build/webpack/loaders/next-flight-action-entry-loader.js?actions=%5B%5B%22C%3A%5C%5CUsers%5C%5Ckompik%5C%5CDocuments%5C%5CVScode%5C%5Csezony%5C%5Csrc%5C%5Capp%5C%5Cadmin%5C%5Crequests%5C%5Cactions.ts%22%2C%5B%22markRequestAction%22%5D%5D%5D&__client_imported__=!"
      },
      "layer": {
        "app/admin/requests/page": "rsc"
      }
    }
  },
  "edge": {},
  "encryptionKey": "PJT1MsvtXeZnwoaU8JEYglaPNPGHq2qnx9OdR5nwyco="
}